icrypto/__init__.py
icrypto/__version__.py
icrypto/icrypto.py
icrypto-0.0.2.dist-info/LICENSE
icrypto-0.0.2.dist-info/METADATA
icrypto-0.0.2.dist-info/WHEEL
icrypto-0.0.2.dist-info/top_level.txt
icrypto-0.0.2.dist-info/RECORD
